nanotext/__init__.py
nanotext/io.py
nanotext/utils.py
nanotext-0.0.1.dist-info/LICENSE
nanotext-0.0.1.dist-info/METADATA
nanotext-0.0.1.dist-info/WHEEL
nanotext-0.0.1.dist-info/top_level.txt
nanotext-0.0.1.dist-info/RECORD
