Metadata-Version: 2.1
Name: nanotext
Version: 0.0.1
Summary: Domains as words, genomes as documents.
Home-page: UNKNOWN
Author: Adrian Viehweger
Author-email: adrian.viehweger@googlemail.com
License: UNKNOWN
Platform: UNKNOWN
Classifier: Programming Language :: Python :: 3
Classifier: License :: OSI Approved :: MIT License
Classifier: Operating System :: OS Independent
